jsonpaths/__init__.py
jsonpaths/jshcema.py
jsonpaths/json_paths.py
json_paths-0.0.9.dist-info/METADATA
json_paths-0.0.9.dist-info/WHEEL
json_paths-0.0.9.dist-info/RECORD
