Metadata-Version: 2.1
Name: json-paths
Version: 0.0.9
Summary: A small library for working with JSON files
Requires-Python: >=3.8
Requires-Dist: pandas
